addic7ed/__init__.py
addic7ed/config.py
addic7ed/constants.py
addic7ed/file_crawler.py
addic7ed/logger.py
addic7ed/parser.py
addic7ed/shows.py
addic7ed-1.1.5.dist-info/DESCRIPTION.rst
addic7ed-1.1.5.dist-info/METADATA
addic7ed-1.1.5.dist-info/RECORD
addic7ed-1.1.5.dist-info/WHEEL
addic7ed-1.1.5.dist-info/entry_points.txt
addic7ed-1.1.5.dist-info/metadata.json
addic7ed-1.1.5.dist-info/top_level.txt
