Metadata-Version: 2.0
Name: addic7ed
Version: 1.1.5
Summary: Addic7ed scraper written in Python to download subtitles (almost) automatically
Home-page: https://github.com/Jesus-21/addic7ed
Author: Adrian MAURIN
Author-email: adrian.maurin@gmail.com
License: MIT
Keywords: subtitles addic7ed scraper
Platform: UNKNOWN
Classifier: Development Status :: 4 - Beta
Classifier: Environment :: Console
Classifier: Intended Audience :: End Users/Desktop
Classifier: License :: OSI Approved :: MIT License
Classifier: Natural Language :: English
Classifier: Operating System :: MacOS
Classifier: Operating System :: Microsoft :: Windows
Classifier: Operating System :: POSIX :: Linux
Classifier: Operating System :: Unix
Classifier: Programming Language :: Python :: 3
Classifier: Topic :: Internet :: WWW/HTTP :: Indexing/Search
Requires-Dist: beautifulsoup4
Requires-Dist: fuzzywuzzy
Requires-Dist: python-Levenshtein
Requires-Dist: requests
Requires-Dist: termcolor
